MANIFEST.in
README.md
setup.py
pulsekit/README.md
pulsekit/__init__.py
pulsekit/core.py
pulsekit/license.txt
pulsekit/resources.py
pulsekit/setup.cfg
pulsekit.egg-info/PKG-INFO
pulsekit.egg-info/SOURCES.txt
pulsekit.egg-info/dependency_links.txt
pulsekit.egg-info/not-zip-safe
pulsekit.egg-info/top_level.txt
pulsekit/__pycache__/__init__.cpython-312.pyc
pulsekit/__pycache__/core.cpython-312.pyc