Metadata-Version: 2.1
Name: pulsekit
Version: 0.0.3
Author: author
Author-email: germanespinosa@gmail.com
